soma_workflow/MPI_workflow_runner.py
soma_workflow/__init__.py
soma_workflow/clean_server.py
soma_workflow/client.py
soma_workflow/client_types.py
soma_workflow/configuration.py
soma_workflow/connection.py
soma_workflow/constants.py
soma_workflow/custom_jobs.py
soma_workflow/database_server.py
soma_workflow/engine.py
soma_workflow/engine_types.py
soma_workflow/errors.py
soma_workflow/info.py
soma_workflow/observer.py
soma_workflow/param_link_functions.py
soma_workflow/scheduler.py
soma_workflow/setup_client2server.py
soma_workflow/setup_server.py
soma_workflow/sro.py
soma_workflow/start_database_server.py
soma_workflow/start_workflow_engine.py
soma_workflow/subprocess.py
soma_workflow/transfer.py
soma_workflow/utils.py
soma_workflow/version.py
soma_workflow/zro.py
soma_workflow/check_requirement/__init__.py
soma_workflow/check_requirement/__main__.py
soma_workflow/check_requirement/drmaa.py
soma_workflow/gui/GroupInfo.ui
soma_workflow/gui/JobInfo.ui
soma_workflow/gui/PlotWidget.ui
soma_workflow/gui/RequirePW.ui
soma_workflow/gui/ServerManagement.ui
soma_workflow/gui/ServerNewDlg.ui
soma_workflow/gui/TransferInfo.ui
soma_workflow/gui/__init__.py
soma_workflow/gui/connection_dlg.ui
soma_workflow/gui/engine_controller_widget.ui
soma_workflow/gui/graphWidget.ui
soma_workflow/gui/local_scheduler_widget.ui
soma_workflow/gui/main_window.ui
soma_workflow/gui/resource_wf_select.ui
soma_workflow/gui/search_widget.ui
soma_workflow/gui/submissionDlg.ui
soma_workflow/gui/sw_mini.ui
soma_workflow/gui/wf_status_name_date.ui
soma_workflow/gui/workflowExampleDlg.ui
soma_workflow/gui/workflowGui.py
soma_workflow/gui/icon/done.png
soma_workflow/gui/icon/failed.png
soma_workflow/gui/icon/files_under_edition.png
soma_workflow/gui/icon/group_done.png
soma_workflow/gui/icon/group_failed.png
soma_workflow/gui/icon/group_no_status.png
soma_workflow/gui/icon/group_running.png
soma_workflow/gui/icon/group_warning.png
soma_workflow/gui/icon/kill_delete_pending.png
soma_workflow-6.0.3.dist-info/licenses/LICENSE
soma_workflow-6.0.3.dist-info/METADATA
soma_workflow-6.0.3.dist-info/WHEEL
soma_workflow-6.0.3.dist-info/top_level.txt
soma_workflow-6.0.3.dist-info/RECORD
