Metadata-Version: 2.4
Name: soma-workflow
Version: 6.0.3
Summary: Soma-Workflow. A unified and simple interface to parallel computing resource
Home-page: https://github.com/populse/soma-workflow
Author: Populse team
Author-email: support@brainvisa.info
License: CeCILL-B
Platform: OS Independent
Classifier: Development Status :: 5 - Production/Stable
Classifier: Environment :: Console
Classifier: Environment :: X11 Applications
Classifier: Intended Audience :: Developers
Classifier: Intended Audience :: Science/Research
Classifier: Intended Audience :: Education
Classifier: Operating System :: OS Independent
Classifier: Programming Language :: Python :: 3.6
Classifier: Programming Language :: Python :: 3.7
Classifier: Programming Language :: Python :: 3.8
Classifier: Programming Language :: Python :: 3.9
Classifier: Programming Language :: Python :: 3.10
Classifier: Programming Language :: Python :: 3 :: Only
Classifier: Topic :: Scientific/Engineering
Classifier: Topic :: Utilities
Classifier: Topic :: Software Development :: Libraries
Classifier: Topic :: System :: Distributed Computing
License-File: LICENSE
Requires-Dist: six
Provides-Extra: plotting
Requires-Dist: matplotlib; extra == "plotting"
Provides-Extra: client
Requires-Dist: zmq; extra == "client"
Requires-Dist: paramiko; extra == "client"
Provides-Extra: doc
Requires-Dist: sphinx>=1.0; extra == "doc"
Dynamic: author
Dynamic: author-email
Dynamic: classifier
Dynamic: description
Dynamic: home-page
Dynamic: license
Dynamic: license-file
Dynamic: platform
Dynamic: provides-extra
Dynamic: requires-dist
Dynamic: summary
